{
  "id": "dsp019c67wp402",
  "title_t": [
    "Beaumains"
  ],
  "title_citation_display": [
    "Beaumains"
  ],
  "title_display": "Beaumains",
  "electronic_access_1display": "{\"http://arks.princeton.edu/ark:/88435/dsp019c67wp402\":[\"DataSpace\",\"Citation only\"]}",
  "restrictions_note_display": [
    "This thesis can be viewed in person at the \u003ca href=http://mudd.princeton.edu\u003eMudd Manuscript Library\u003c/a\u003e.  \nTo order a copy complete the \u003ca href=\"http://rbsc.princeton.edu/senior-thesis-order-form\" target=\"_blank\"\u003eSenior Thesis Request Form\u003c/a\u003e.  \nFor more information contact \u003ca href=mailto:mudd@princeton.edu\u003emudd@princeton.edu\u003c/a\u003e."
  ],
  "call_number_display": [
    "AC102 24981"
  ],
  "call_number_browse_s": [
    "AC102 24981"
  ],
  "language_facet": [
    "English"
  ],
  "author_display": [
    "Sobieski, Robert Yan"
  ],
  "author_s": [
    "Sobieski, Robert Yan",
    "Anderson, Sarah",
    "Sobel, Anne",
    "Princeton University. Department of English"
  ],
  "advisor_display": [
    "Anderson, Sarah"
  ],
  "contributor_display": [
    "Sobel, Anne"
  ],
  "department_display": [
    "Princeton University. Department of English"
  ],
  "description_display": [
    "129 Pages"
  ],
  "location": [
    "Mudd Manuscript Library"
  ],
  "location_display": [
    "Mudd Manuscript Library"
  ],
  "location_code_s": [
    "mudd$stacks"
  ],
  "advanced_location_s": [
    "mudd$stacks",
    "Mudd Manuscript Library"
  ],
  "holdings_1display": "{\"thesis\":{\"location\":\"Mudd Manuscript Library\",\"library\":\"Mudd Manuscript Library\",\"location_code\":\"mudd$stacks\",\"call_number\":\"AC102 24981\",\"call_number_browse\":\"AC102 24981\",\"dspace\":true}}",
  "class_year_s": [
    "2010"
  ],
  "pub_date_start_sort": 2010,
  "pub_date_end_sort": 2010,
  "format": [
    "Senior thesis"
  ],
  "hashed_id_s": [
    "cec8fdbe71dfe3dd"
  ]
}
