{
  "id": "dsp017s75dc44p",
  "title_t": [
    "Almost Human: ROBOTS IN ARCHITECTURE AND\r\nTHE NARRATIVE OF CONTROL"
  ],
  "title_citation_display": [
    "Almost Human: ROBOTS IN ARCHITECTURE AND\r\nTHE NARRATIVE OF CONTROL"
  ],
  "title_display": "Almost Human: ROBOTS IN ARCHITECTURE AND\r\nTHE NARRATIVE OF CONTROL",
  "electronic_access_1display": "{\"http://arks.princeton.edu/ark:/88435/dsp017s75dc44p\":[\"DataSpace\",\"Citation only\"]}",
  "restrictions_note_display": [
    "Walk-in Access. This thesis can only be viewed on computer terminals at the <a href=http://mudd.princeton.edu>Mudd Manuscript Library</a>."
  ],
  "call_number_display": [
    "AC102"
  ],
  "call_number_browse_s": [
    "AC102"
  ],
  "language_facet": [
    "English"
  ],
  "author_display": [
    "Auduong, Raymond"
  ],
  "author_s": [
    "Auduong, Raymond",
    "Kilian, Axel",
    "Vertesi, Janet",
    "Princeton University. School of Architecture"
  ],
  "advisor_display": [
    "Kilian, Axel"
  ],
  "contributor_display": [
    "Vertesi, Janet"
  ],
  "department_display": [
    "Princeton University. School of Architecture"
  ],
  "description_display": [
    "93 pages"
  ],
  "location": [
    "Mudd Manuscript Library"
  ],
  "location_display": [
    "Mudd Manuscript Library"
  ],
  "location_code_s": [
    "mudd$stacks"
  ],
  "advanced_location_s": [
    "mudd$stacks",
    "Mudd Manuscript Library"
  ],
  "holdings_1display": "{\"thesis\":{\"location\":\"Mudd Manuscript Library\",\"library\":\"Mudd Manuscript Library\",\"location_code\":\"mudd$stacks\",\"call_number\":\"AC102\",\"call_number_browse\":\"AC102\",\"dspace\":true}}",
  "class_year_s": [
    "2013"
  ],
  "pub_date_start_sort": 2013,
  "pub_date_end_sort": 2013,
  "format": [
    "Senior thesis"
  ]
}