{
    "id": [
        "9918309193506421"
    ],
    "numeric_id_b": [
        true
    ],
    "cjk_all": [
        "波乃耶, 1796-1866. 華番和合通書. 和合通書 刻本, 綫裝. [China]: [波乃耶], 清咸豐2年 [1852] 子部 諸家類 基督教之屬 skbb 子部 天文算法類 曆法. sk 封面題：\"咸豐二年 番自耶穌降生至今一千八百五十二年 華蕃和合通書\". \"Dyer Ball (1796-1866), between 1843 and 1854, Dyer compiled and published one Chinese almanc every year\" --本舘《唐番和合通書》（BT65T364 1861）所附購書介紹. 維基百科\"波乃耶 (傳教士)\" \"棄假歸真論\"首葉框18.5 x 13.5公分, 10行24字, 白口, 四周雙邊, 單黑魚尾. 版心上鐫篇名. 波乃耶(Dyer Ball), 參見維基百科 \"波乃耶 (傳教士)\"條目--2022年5月5日查看."
    ],
    "cjk_notes": [
        "封面題：\"咸豐二年 番自耶穌降生至今一千八百五十二年 華蕃和合通書\". \"Dyer Ball (1796-1866), between 1843 and 1854, Dyer compiled and published one Chinese almanc every year\" --本舘《唐番和合通書》（BT65T364 1861）所附購書介紹. 維基百科\"波乃耶 (傳教士)\" \"棄假歸真論\"首葉框18.5 x 13.5公分, 10行24字, 白口, 四周雙邊, 單黑魚尾. 版心上鐫篇名. 波乃耶(Dyer Ball), 參見維基百科 \"波乃耶 (傳教士)\"條目--2022年5月5日查看."
    ],
    "author_display": [
        "Ball, Dyer, 1796-1866",
        "波乃耶, 1796-1866"
    ],
    "author_sort": [
        "Ball, Dyer, 1796-1866"
    ],
    "author_citation_display": [
        "Ball, Dyer",
        "Chinese Rare Books Project"
    ],
    "author_roles_1display": [
        "{\"secondary_authors\":[\"波乃耶\",\"Chinese Rare Books Project\"],\"translators\":[],\"editors\":[],\"compilers\":[],\"primary_author\":\"Ball, Dyer\"}"
    ],
    "cjk_author": [
        "波乃耶, 1796-1866"
    ],
    "author_s": [
        "Ball, Dyer, 1796-1866",
        "波乃耶, 1796-1866",
        "Chinese Rare Books Project Post-1795 books"
    ],
    "marc_relator_display": [
        "Author"
    ],
    "title_display": [
        "Hua fan he he tong shu."
    ],
    "title_a_index": [
        "Hua fan he he tong shu",
        "華番和合通書"
    ],
    "title_vern_display": [
        "華番和合通書."
    ],
    "title_sort": [
        "Hua fan he he tong shu."
    ],
    "title_vern_sort": [
        "華番和合通書."
    ],
    "title_no_h_index": [
        "Hua fan he he tong shu.",
        "華番和合通書."
    ],
    "title_t": [
        "Hua fan he he tong shu."
    ],
    "title_citation_display": [
        "Hua fan he he tong shu",
        "華番和合通書"
    ],
    "cjk_title": [
        "華番和合通書.",
        "和合通書"
    ],
    "compiled_created_t": [
        "Hua fan he he tong shu.",
        "華番和合通書."
    ],
    "edition_display": [
        "Ke ben, xian zhuang.",
        "刻本, 綫裝."
    ],
    "pub_created_vern_display": [
        "[China]: [波乃耶], 清咸豐2年 [1852]"
    ],
    "pub_created_display": [
        "[China]: [bonaiye], Qing Xianfeng 2 nian [1852]",
        "[China]: [波乃耶], 清咸豐2年 [1852]"
    ],
    "pub_created_s": [
        "[China]: [bonaiye], Qing Xianfeng 2 nian [1852]",
        "[China]: [波乃耶], 清咸豐2年 [1852]"
    ],
    "pub_citation_display": [
        "China: bonaiye",
        "China: 波乃耶"
    ],
    "publication_location_citation_display": [
        "China"
    ],
    "publisher_citation_display": [
        "bonaiye"
    ],
    "pub_date_display": [
        "1852"
    ],
    "pub_date_start_sort": [
        "1852"
    ],
    "publication_date_citation_display": [
        "1852"
    ],
    "cataloged_tdt": [
        "2000-06-13T00:00:00Z"
    ],
    "format": [
        "Book"
    ],
    "electronic_access_1display": [
        "{\"https://catalog.princeton.edu/catalog/9918309193506421#view\":[\"Book preliminaries\"],\"iiif_manifest_paths\":{\"http://arks.princeton.edu/ark:/88435/dccf95jp00m\":\"https://figgy.princeton.edu/concern/scanned_resources/b6201a98-e08b-47df-ab93-2455826dfeef/manifest\"}}"
    ],
    "electronic_access_index": [
        "Book preliminaries http://arks.princeton.edu/ark:/88435/dccf95jp00m"
    ],
    "description_display": [
        "1 volume : illustrations, maps ; 27 cm"
    ],
    "description_t": [
        "1 volume : illustrations, maps ; 27 cm"
    ],
    "number_of_pages_citation_display": [
        "1 volume"
    ],
    "notes_display": [
        "封面題：\"咸豐二年 番自耶穌降生至今一千八百五十二年 華蕃和合通書\".",
        "\"Dyer Ball (1796-1866), between 1843 and 1854, Dyer compiled and published one Chinese almanc every year\" --本舘《唐番和合通書》（BT65T364 1861）所附購書介紹. 維基百科\"波乃耶 (傳教士)\"",
        "\"棄假歸真論\"首葉框18.5 x 13.5公分, 10行24字, 白口, 四周雙邊, 單黑魚尾. 版心上鐫篇名."
    ],
    "language_name_display": [
        "Chinese"
    ],
    "language_facet": [
        "Chinese"
    ],
    "publication_place_facet": [
        "China"
    ],
    "language_iana_s": [
        "zh"
    ],
    "references_display": [
        "波乃耶(Dyer Ball), 參見維基百科 \"波乃耶 (傳教士)\"條目--2022年5月5日查看."
    ],
    "references_url_display": [
        "波乃耶(Dyer Ball), 參見維基百科 \"波乃耶 (傳教士)\"條目--2022年5月5日查看."
    ],
    "lc_subject_display": [
        "Theology, Doctrinal",
        "Almanacs, Chinese"
    ],
    "lc_subject_include_archaic_search_terms_index": [
        "Theology, Doctrinal",
        "Almanacs, Chinese"
    ],
    "siku_subject_display": [
        "Zi bu—Zhu jia lei—Jidu jiao zhi shu",
        "子部—諸家類—基督教之屬",
        "Zi bu—Tian wen suan fa lei—Li fa.",
        "子部—天文算法類—曆法."
    ],
    "siku_subject_facet": [
        "Zi bu",
        "Zi bu—Zhu jia lei",
        "Zi bu—Zhu jia lei—Jidu jiao zhi shu",
        "子部",
        "子部—諸家類",
        "子部—諸家類—基督教之屬",
        "Zi bu—Tian wen suan fa lei",
        "Zi bu—Tian wen suan fa lei—Li fa.",
        "子部—天文算法類",
        "子部—天文算法類—曆法."
    ],
    "subject_unstem_search": [
        "Theology, Doctrinal",
        "Almanacs, Chinese"
    ],
    "local_subject_unstem_search": null,
    "siku_subject_unstem_search": [
        "Zi bu—Zhu jia lei—Jidu jiao zhi shu",
        "子部—諸家類—基督教之屬",
        "Zi bu—Tian wen suan fa lei—Li fa.",
        "子部—天文算法類—曆法."
    ],
    "homoit_subject_unstem_search": null,
    "fast_subject_unstem_search": null,
    "subject_facet": [
        "Theology, Doctrinal",
        "Almanacs, Chinese",
        "Zi bu—Zhu jia lei—Jidu jiao zhi shu",
        "子部—諸家類—基督教之屬",
        "Zi bu—Tian wen suan fa lei—Li fa.",
        "子部—天文算法類—曆法."
    ],
    "lc_subject_facet": [
        "Theology, Doctrinal",
        "Almanacs, Chinese"
    ],
    "publication_place_hierarchical_facet": [
        "China"
    ],
    "cjk_subject": [
        "子部 諸家類 基督教之屬",
        "子部 天文算法類 曆法."
    ],
    "subject_topic_facet": [
        "Theology, Doctrinal",
        "Almanacs, Chinese",
        "Zi bu",
        "Zhu jia lei",
        "Jidu jiao zhi shu",
        "子部",
        "諸家類",
        "基督教之屬",
        "Tian wen suan fa lei",
        "Li fa.",
        "天文算法類",
        "曆法."
    ],
    "related_name_json_1display": [
        "{\"Related name\":[\"Chinese Rare Books Project Post-1795 books\"]}"
    ],
    "other_title_index": [
        "He he tong shu",
        "和合通書"
    ],
    "other_title_display": [
        "He he tong shu",
        "和合通書"
    ],
    "alt_title_246_display": [
        "He he tong shu",
        "和合通書"
    ],
    "oclc_s": [
        "63184220"
    ],
    "standard_no_index": [
        "1830919-princetondb",
        "ocm63184220"
    ],
    "other_version_s": [
        "ocm63184220"
    ],
    "holdings_1display": [
        "{\"22645461280006421\":{\"location_code\":\"eastasian$pl\",\"location\":\"Remote Storage (ReCAP): East Asian Library Use Only\",\"library\":\"East Asian Library\",\"call_number\":\"9315/4228\",\"call_number_browse\":\"9315/4228\",\"items\":[{\"holding_id\":\"22645461280006421\",\"id\":\"23645461270006421\",\"status_at_load\":\"0\",\"barcode\":\"32101087243331\",\"copy_number\":\"1\",\"process_type\":\"TRANSIT\"}]}}"
    ],
    "location_code_s": [
        "eastasian$pl"
    ],
    "location": [
        "East Asian Library"
    ],
    "location_display": [
        "Remote Storage (ReCAP): East Asian Library Use Only"
    ],
    "advanced_location_s": [
        "eastasian$pl",
        "East Asian Library"
    ],
    "name_title_browse_s": [
        "Ball, Dyer, 1796-1866. Hua fan he he tong shu",
        "波乃耶, 1796-1866. 華番和合通書"
    ],
    "call_number_display": [
        "9315/4228"
    ],
    "call_number_browse_s": [
        "9315/4228"
    ],
    "call_number_locator_display": [
        "9315/4228"
    ],
    "access_facet": [
        "In the Library",
        "Online"
    ]
}